README.rst
setup.py
src/fc_vfemp1_eigs/__init__.py
src/fc_vfemp1_eigs/lib.py
src/fc_vfemp1_eigs/matplotlib.py
src/fc_vfemp1_eigs/mayavi.py
src/fc_vfemp1_eigs/sys.py
src/fc_vfemp1_eigs.egg-info/PKG-INFO
src/fc_vfemp1_eigs.egg-info/SOURCES.txt
src/fc_vfemp1_eigs.egg-info/dependency_links.txt
src/fc_vfemp1_eigs.egg-info/requires.txt
src/fc_vfemp1_eigs.egg-info/top_level.txt
src/fc_vfemp1_eigs/examples/ConvectionDiffusion_Dir_Lshape_2D01.py
src/fc_vfemp1_eigs/examples/Laplacian_Dir_Lshape_2D01.py
src/fc_vfemp1_eigs/examples/Laplacian_Mixed_disk5holes_2D01.py
src/fc_vfemp1_eigs/examples/LinearElasticity_spacial.py
src/fc_vfemp1_eigs/examples/LinearElasticity_tidal_turbine.py
src/fc_vfemp1_eigs/examples/LinearElasticity_tuning_fork2D02.py
src/fc_vfemp1_eigs/examples/LinearElasticity_tuning_fork3D02.py
src/fc_vfemp1_eigs/examples/LinearElasticity_tuning_fork3D02_light.py
src/fc_vfemp1_eigs/examples/__init__.py
src/fc_vfemp1_eigs/examples/biharmonic_Mixed_disk5holes.py
src/fc_vfemp1_eigs/examples/biharmonic_SSP_disk5holes.py
src/fc_vfemp1_eigs/examples/biharmonic_SSP_rectangle_ex.py
src/fc_vfemp1_eigs/examples/laplacian_DDDD_rectangle_ex.py
src/fc_vfemp1_eigs/examples/laplacian_Dirichlet.py
src/fc_vfemp1_eigs/examples/laplacian_Dirichlet_disk4bounds.py
src/fc_vfemp1_eigs/geodir/2d/Lshape.geo
src/fc_vfemp1_eigs/geodir/2d/disk4bounds.geo
src/fc_vfemp1_eigs/geodir/2d/options01_data.geo
src/fc_vfemp1_eigs/geodir/2d/rect4.geo
src/fc_vfemp1_eigs/geodir/2d/rectangle-3-by-2-4bounds.geo
src/fc_vfemp1_eigs/geodir/2d/shape_functions.geo
src/fc_vfemp1_eigs/geodir/2d/square1holev2.geo
src/fc_vfemp1_eigs/geodir/2d/tuning-fork2D02.geo
src/fc_vfemp1_eigs/geodir/3d/TuningFork440Hz.geo
src/fc_vfemp1_eigs/geodir/3d/construction02.geo
src/fc_vfemp1_eigs/geodir/3d/diapason.geo
src/fc_vfemp1_eigs/geodir/3d/spacial.geo
src/fc_vfemp1_eigs/geodir/3d/tidal_turbine.geo
src/fc_vfemp1_eigs/geodir/3d/tuning_fork_01.geo
src/fc_vfemp1_eigs/geodir/3d/tuning_fork_02.geo